<?xml version="1.0" encoding="UTF-8" standalone="no"?><Empleados><empleado><id>1</id><apellido>Fernandez</apellido><dep>10</dep><salario>1000.45</salario></empleado><empleado><id>2</id><apellido>Gil</apellido><dep>20</dep><salario>2400.60</salario></empleado><empleado><id>3</id><apellido>Lopez</apellido><dep>10</dep><salario>3000.10</salario></empleado><empleado><id>4</id><apellido>Ramos</apellido><dep>10</dep><salario>1520.35</salario></empleado><empleado><id>5</id><apellido>Caldeiro</apellido><dep>20</dep><salario>15550.75</salario></empleado></Empleados>